APIKL/APIKL.py
APIKL/Found.py
APIKL/__init__.py
APIKL-1.2.dist-info/LICENSE
APIKL-1.2.dist-info/METADATA
APIKL-1.2.dist-info/WHEEL
APIKL-1.2.dist-info/top_level.txt
APIKL-1.2.dist-info/RECORD
