Metadata-Version: 2.1
Name: APIKL
Version: 1.2
Summary: This module allows you to find API keys and passwords in your project.
Home-page: https://github.com/VitalyKalinsky/APIKL
Author: Vitaly_Kalinsky
Author-email: kalinskyvii@gmail.com
Project-URL: GitHub, https://github.com/VitalyKalinsky
Keywords: API keys APIkeys locate detect passwords
Classifier: Programming Language :: Python :: 3.12
Classifier: License :: OSI Approved :: MIT License
Classifier: Operating System :: OS Independent
Requires-Python: >=3.12.2
License-File: LICENSE
